bitnob/__init__.py
bitnob/base.py
bitnob/model.py
bitnob/customer/__init__.py
bitnob/customer/model.py
bitnob/customer/services.py
bitnob/exceptions/__init__.py
bitnob/exceptions/exceptions.py
bitnob/hosted_checkout/__init__.py
bitnob/hosted_checkout/model.py
bitnob/hosted_checkout/services.py
bitnob/lightning/__init__.py
bitnob/lightning/model.py
bitnob/lightning/services.py
bitnob/ln_url/__init__.py
bitnob/ln_url/model.py
bitnob/ln_url/services.py
bitnob/onchain/__init__.py
bitnob/onchain/model.py
bitnob/onchain/services.py
bitnob/stablecoin/__init__.py
bitnob/stablecoin/model.py
bitnob/stablecoin/services.py
bitnob/virtual_card/__init__.py
bitnob/virtual_card/model.py
bitnob/virtual_card/services.py
bitnob/wallet/__init__.py
bitnob/wallet/model.py
bitnob/wallet/services.py
tests/__init__.py
tests/test_customer.py
tests/test_onchain.py
tests/test_stablecoins.py
bitnob-1.3.1.dist-info/METADATA
bitnob-1.3.1.dist-info/WHEEL
bitnob-1.3.1.dist-info/top_level.txt
bitnob-1.3.1.dist-info/RECORD
