Metadata-Version: 2.1
Name: bitnob
Version: 1.3.1
Summary: Python SDK for the Bitnob"s API
Home-page: https://github.com/bitnob/bitnob_python_sdk
Author: Bitnob
Author-email: info@bitnob.com
License: MIT
Platform: UNKNOWN
Classifier: License :: OSI Approved :: MIT License
Classifier: Programming Language :: Python :: 3
Classifier: Programming Language :: Python :: 3.6
Classifier: Programming Language :: Python :: 3.7
Requires-Python: >=3.6
Requires-Dist: requests
